{
    "key": "group_5fb668cb66b2e",
    "title": "parallax-gallery",
    "fields": [
        {
            "key": "field_5fb668d8d0ca0",
            "label": "parallax-gallery",
            "name": "parallax-gallery",
            "type": "gallery",
            "instructions": "",
            "required": 0,
            "conditional_logic": 0,
            "wrapper": {
                "width": "",
                "class": "",
                "id": ""
            },
            "return_format": "array",
            "preview_size": "medium",
            "insert": "append",
            "library": "all",
            "min": 1,
            "max": 4,
            "min_width": "",
            "min_height": "",
            "min_size": "",
            "max_width": "",
            "max_height": "",
            "max_size": "",
            "mime_types": ""
        }
    ],
    "location": [
        [
            {
                "param": "page_template",
                "operator": "==",
                "value": "homepage.php"
            }
        ]
    ],
    "menu_order": 0,
    "position": "normal",
    "style": "default",
    "label_placement": "top",
    "instruction_placement": "label",
    "hide_on_screen": "",
    "active": true,
    "description": "",
    "modified": 1605821505
}